apimapper/__init__.py
apimapper/apimapper.py
apimapper/responsemapper.py
apimapper/config/__init__.py
apimapper/config/config.py
apimapper/config/demo.py
apimapper/tests/__init__.py
apimapper/tests/test_apimapper.py
apimapper-0.7.9.dist-info/LICENSE
apimapper-0.7.9.dist-info/METADATA
apimapper-0.7.9.dist-info/WHEEL
apimapper-0.7.9.dist-info/top_level.txt
apimapper-0.7.9.dist-info/RECORD
