Metadata-Version: 2.1
Name: apimapper
Version: 0.7.9
Summary: API Mapper
Home-page: https://github.com/acdh-oeaw/apimapper
Author: Saranya Balasubramanian, Ksenia Zaytseva
Author-email: saranya.balasubramanian@oeaw.ac.at
License: MIT
Keywords: API Mapper
Classifier: Development Status :: 3 - Alpha
Classifier: License :: OSI Approved :: MIT License
Classifier: Programming Language :: Python :: 3.6
Classifier: Topic :: Scientific/Engineering :: Information Analysis
License-File: LICENSE
Requires-Dist: markdown
Requires-Dist: requests
